tiegcmpy/__init__.py
tiegcmpy/convert_units.py
tiegcmpy/data_emissions.py
tiegcmpy/data_parse.py
tiegcmpy/getoptions.py
tiegcmpy/getoptions_old.py
tiegcmpy/io.py
tiegcmpy/main.py
tiegcmpy/mov_gen.py
tiegcmpy/mov_gen_old.py
tiegcmpy/plot_gen.py
tiegcmpy/plot_gen_old.py
tiegcmpy/cmd/__init__.py
tiegcmpy/cmd/cmd_lat_lon.py
tiegcmpy/cmd/cmd_lat_time.py
tiegcmpy/cmd/cmd_lev_lat.py
tiegcmpy/cmd/cmd_lev_lon.py
tiegcmpy/cmd/cmd_lev_time.py
tiegcmpy/cmd/cmd_lev_var.py
tiegcmpy-2.1.0.dist-info/METADATA
tiegcmpy-2.1.0.dist-info/WHEEL
tiegcmpy-2.1.0.dist-info/entry_points.txt
tiegcmpy-2.1.0.dist-info/top_level.txt
tiegcmpy-2.1.0.dist-info/RECORD
