Metadata-Version: 2.1
Name: tiegcmpy
Version: 2.1.0
Summary: A Python3 post processing tool for TIE-GCM
Home-page: https://github.com/NCAR/tiegcmpy
Author: Nikhil Rao
Author-email: nikhilr@ucar.edu
Requires-Python: >=3.8
Requires-Dist: cartopy
Requires-Dist: matplotlib
Requires-Dist: numpy
Requires-Dist: xarray
Requires-Dist: ipython
Requires-Dist: geomag
